corcovado/__init__.py
corcovado/api/timer.py
corcovado/cli.py
corcovado/database/__init__.py
corcovado/database/main.py
corcovado/database/models.py
corcovado/database/repository.py
corcovado/database/settings.py
corcovado-0.1.0.dist-info/WHEEL
corcovado-0.1.0.dist-info/METADATA
corcovado-0.1.0.dist-info/RECORD
