Metadata-Version: 2.1
Name: corcovado
Version: 0.1.0
Summary: 
Author: Alexandre Xavier
Author-email: ale.bxsantos@gmail.com
Requires-Python: >=3.9,<4.0
Classifier: Programming Language :: Python :: 3
Classifier: Programming Language :: Python :: 3.9
Requires-Dist: SQLAlchemy (>=1.3.23,<2.0.0)
Requires-Dist: SQLAlchemy-Utils (>=0.36.8,<0.37.0)
Requires-Dist: click (>=7.1.2,<8.0.0)
Requires-Dist: pyfiglet (>=0.8.post1,<0.9)
Requires-Dist: pytest-mock (>=3.5.1,<4.0.0)
Requires-Dist: python-dateutil (>=2.8.1,<3.0.0)
Requires-Dist: rich (>=9.10.0,<10.0.0)
Requires-Dist: typer (>=0.3.2,<0.4.0)
